{
  "timestamp": "2026-06-23T11:41:18.458293+00:00",
  "signal": {
    "price": 0.9726,
    "xgb_pred": "DOWN",
    "xgb_prob": 0.2951,
    "hybrid_score": 3.0,
    "regime": "BEARISH",
    "entry_signal": false,
    "exit_signal": true,
    "action": "SELL",
    "news": {
      "sentiment": "NEUTRAL",
      "score": 0.03,
      "bullish_pct": 31.7,
      "bearish_pct": 25.0,
      "headlines_analyzed": 60,
      "feed_scores": {
        "xrp": 0.214,
        "crypto_macro": -0.048,
        "geopolitical": -0.333,
        "fed_rates": 0.177
      },
      "geo_shock": true,
      "geo_dip": {
        "active": false,
        "buy_signal": false,
        "phase": "NONE"
      },
      "crypto_specific_bad": false,
      "news_driven_crash": false,
      "top_bullish": [
        "Here's what seven straight weeks of ETF inflows mean for XRP - FXStreet",
        "Ripple secures preliminary approval in EU through Luxembourg MiCA license - CoinDesk",
        "Ripple\u2019s IPO could reward XRP holders. What we actually know - crypto.news"
      ],
      "top_bearish": [
        "The crisis in the Strait of Hormuz will not replay itself in the South China Sea - Lowy Institute",
        "Strait of Hormuz traffic flowing slowly as US, Iran trade threats - Yahoo Finance",
        "Elon Musk Grok AI Predicts Shocking XRP Price by End of 2026 - Cryptonews"
      ]
    },
    "vpa": {
      "phase": "DISTRIBUTION",
      "up_down_ratio": 0.81,
      "health": -0.0847,
      "vol_ratio": 0.23
    },
    "technicals": {
      "ema50": 0.96952,
      "ema200": 0.9787,
      "macd": 0.001276,
      "macd_signal": 0.000598,
      "rsi14": 68.8,
      "atr14": 0.00138,
      "atr14_hourly": 0.00639,
      "bb_position": 0.924
    },
    "trade_feedback": {
      "loss_streak": 3,
      "recent_win_rate": 0.125,
      "entry_prob_adjusted": 0.6,
      "adapted_sl_mult": 1.5,
      "adapted_tp_mult": 2.5
    }
  },
  "trade": {
    "action": "HOLD",
    "reason": "STAY CASH: waiting for BUY signal (model=SELL)",
    "portfolio_eur": 4922.43,
    "total_pnl_pct": -1.551,
    "position": "CASH",
    "xrp_held": 0.0,
    "cash_eur": 4922.43,
    "trade_count": 46,
    "draw_levels": {}
  },
  "trade_feedback": {
    "overall_win_rate": 0.435,
    "recent_win_rate": 0.125,
    "avg_win_pct": 0.492,
    "avg_loss_pct": -0.495,
    "loss_streak": 3,
    "win_streak": 0,
    "total_wins": 10,
    "total_losses": 13,
    "loss_reasons": {
      "MODEL_SELL": 12,
      "STOP_LOSS": 1
    },
    "sl_loss_ratio": 0.077,
    "model_loss_ratio": 0.923,
    "adapted_sl_mult": 1.5,
    "adapted_tp_mult": 2.5,
    "score_adjustment": 1,
    "entry_prob_effective": 0.6
  },
  "retrained": true,
  "data_bars": 158559
}